pixelart/pixelart.py
vpype_pixelart-0.4.0.dist-info/LICENSE
vpype_pixelart-0.4.0.dist-info/METADATA
vpype_pixelart-0.4.0.dist-info/WHEEL
vpype_pixelart-0.4.0.dist-info/entry_points.txt
vpype_pixelart-0.4.0.dist-info/top_level.txt
vpype_pixelart-0.4.0.dist-info/RECORD
