Metadata-Version: 2.1
Name: vpype-pixelart
Version: 0.4.0
Summary: Pixel art plug-in for vpype
Home-page: https://github.com/abey79/vpype-pixelart
Author: Antoine Beyeler
Classifier: Development Status :: 4 - Beta
Classifier: License :: OSI Approved :: MIT License
Classifier: Topic :: Multimedia :: Graphics
Classifier: Environment :: Plugins
License-File: LICENSE
Requires-Dist: click
Requires-Dist: numpy
Requires-Dist: Pillow
Requires-Dist: vpype[all] (<2.0,>=1.10)
